[
  {
    "line": 1,
    "elements": [
      {
        "line": 3,
        "name": "go to apec home page",
        "description": "",
        "type": "background",
        "keyword": "Background",
        "steps": [
          {
            "result": {
              "duration": 12366000000,
              "status": "passed"
            },
            "line": 4,
            "name": "User is on Apec home page",
            "match": {
              "location": "com.apec.stepDefinitions.Bug621Stepdefs.userIsOnApecHomePage()"
            },
            "keyword": "Given "
          }
        ]
      },
      {
        "start_timestamp": "2021-06-11T15:24:37.911Z",
        "before": [
          {
            "result": {
              "duration": 5378000000,
              "status": "passed"
            },
            "match": {
              "location": "com.apec.stepDefinitions.CucumberHooks.setup()"
            }
          }
        ],
        "line": 6,
        "name": "Bug 621 Contactez-nous link redirectionerror",
        "description": "",
        "id": "apec-bugs;bug-621-contactez-nous-link-redirectionerror",
        "after": [
          {
            "result": {
              "duration": 542000000,
              "status": "passed"
            },
            "match": {
              "location": "com.apec.stepDefinitions.CucumberHooks.teardown()"
            }
          }
        ],
        "type": "scenario",
        "keyword": "Scenario",
        "steps": [
          {
            "result": {
              "duration": 7661000000,
              "status": "passed"
            },
            "line": 7,
            "name": "User clicked on site corporate link",
            "match": {
              "location": "com.apec.stepDefinitions.Bug621Stepdefs.userClickedOnSiteCorporateLink()"
            },
            "keyword": "And "
          },
          {
            "result": {
              "duration": 73000000,
              "status": "passed"
            },
            "line": 8,
            "name": "user clicked on contactez-nous link",
            "match": {
              "location": "com.apec.stepDefinitions.Bug621Stepdefs.userClickedOnContactezNousLink()"
            },
            "keyword": "When "
          },
          {
            "result": {
              "error_message": "java.lang.AssertionError: expected [true] but found [false]\n\tat org.testng.Assert.fail(Assert.java:99)\n\tat org.testng.Assert.failNotEquals(Assert.java:1037)\n\tat org.testng.Assert.assertTrue(Assert.java:45)\n\tat org.testng.Assert.assertTrue(Assert.java:55)\n\tat com.apec.utils.BaseClass.checkCorrection(BaseClass.java:130)\n\tat com.apec.pages.CorporatePage.verificationBug621(CorporatePage.java:36)\n\tat com.apec.stepDefinitions.Bug621Stepdefs.userShouldBeOnContactPage(Bug621Stepdefs.java:36)\n\tat ✽.User should be on contact page(file:///Users/dylanIsrael/IdeaProjects/cucumber/ApecTestAutomation/src/test/resources/features/Apec.feature:9)\n",
              "duration": 1081000000,
              "status": "failed"
            },
            "line": 9,
            "name": "User should be on contact page",
            "match": {
              "location": "com.apec.stepDefinitions.Bug621Stepdefs.userShouldBeOnContactPage()"
            },
            "keyword": "Then "
          }
        ]
      },
      {
        "line": 3,
        "name": "go to apec home page",
        "description": "",
        "type": "background",
        "keyword": "Background",
        "steps": [
          {
            "result": {
              "duration": 9099000000,
              "status": "passed"
            },
            "line": 4,
            "name": "User is on Apec home page",
            "match": {
              "location": "com.apec.stepDefinitions.Bug621Stepdefs.userIsOnApecHomePage()"
            },
            "keyword": "Given "
          }
        ]
      },
      {
        "start_timestamp": "2021-06-11T15:25:05.157Z",
        "before": [
          {
            "result": {
              "duration": 2960000000,
              "status": "passed"
            },
            "match": {
              "location": "com.apec.stepDefinitions.CucumberHooks.setup()"
            }
          }
        ],
        "line": 16,
        "name": "Bug 604 button overlapping",
        "description": "",
        "id": "apec-bugs;bug-604-button-overlapping;;2",
        "after": [
          {
            "result": {
              "duration": 412000000,
              "status": "passed"
            },
            "match": {
              "location": "com.apec.stepDefinitions.CucumberHooks.teardown()"
            }
          }
        ],
        "type": "scenario",
        "keyword": "Scenario Outline",
        "steps": [
          {
            "result": {
              "duration": 3225000000,
              "status": "passed"
            },
            "line": 12,
            "name": "User set windows size with 768 and 1024",
            "match": {
              "arguments": [
                {
                  "val": "768",
                  "offset": 27
                },
                {
                  "val": "1024",
                  "offset": 35
                }
              ],
              "location": "com.apec.stepDefinitions.Bug604Stepdefs.userSetWindowsSizeWithWidthAndHeight(int,int)"
            },
            "keyword": "When "
          },
          {
            "result": {
              "error_message": "java.lang.AssertionError: expected [true] but found [false]\n\tat org.testng.Assert.fail(Assert.java:99)\n\tat org.testng.Assert.failNotEquals(Assert.java:1037)\n\tat org.testng.Assert.assertTrue(Assert.java:45)\n\tat org.testng.Assert.assertTrue(Assert.java:55)\n\tat com.apec.utils.BaseClass.checkCorrection(BaseClass.java:130)\n\tat com.apec.pages.HomePage.verifictionBug604(HomePage.java:68)\n\tat com.apec.stepDefinitions.Bug604Stepdefs.elementsAreOverlapping(Bug604Stepdefs.java:20)\n\tat ✽.Elements are overlapping(file:///Users/dylanIsrael/IdeaProjects/cucumber/ApecTestAutomation/src/test/resources/features/Apec.feature:13)\n",
              "duration": 90000000,
              "status": "failed"
            },
            "line": 13,
            "name": "Elements are overlapping",
            "match": {
              "location": "com.apec.stepDefinitions.Bug604Stepdefs.elementsAreOverlapping()"
            },
            "keyword": "Then "
          }
        ]
      },
      {
        "line": 3,
        "name": "go to apec home page",
        "description": "",
        "type": "background",
        "keyword": "Background",
        "steps": [
          {
            "result": {
              "duration": 6268000000,
              "status": "passed"
            },
            "line": 4,
            "name": "User is on Apec home page",
            "match": {
              "location": "com.apec.stepDefinitions.Bug621Stepdefs.userIsOnApecHomePage()"
            },
            "keyword": "Given "
          }
        ]
      },
      {
        "start_timestamp": "2021-06-11T15:25:20.962Z",
        "before": [
          {
            "result": {
              "duration": 2050000000,
              "status": "passed"
            },
            "match": {
              "location": "com.apec.stepDefinitions.CucumberHooks.setup()"
            }
          }
        ],
        "line": 17,
        "name": "Bug 604 button overlapping",
        "description": "",
        "id": "apec-bugs;bug-604-button-overlapping;;3",
        "after": [
          {
            "result": {
              "duration": 359000000,
              "status": "passed"
            },
            "match": {
              "location": "com.apec.stepDefinitions.CucumberHooks.teardown()"
            }
          }
        ],
        "type": "scenario",
        "keyword": "Scenario Outline",
        "steps": [
          {
            "result": {
              "duration": 3258000000,
              "status": "passed"
            },
            "line": 12,
            "name": "User set windows size with 1620 and 2160",
            "match": {
              "arguments": [
                {
                  "val": "1620",
                  "offset": 27
                },
                {
                  "val": "2160",
                  "offset": 36
                }
              ],
              "location": "com.apec.stepDefinitions.Bug604Stepdefs.userSetWindowsSizeWithWidthAndHeight(int,int)"
            },
            "keyword": "When "
          },
          {
            "result": {
              "duration": 96000000,
              "status": "passed"
            },
            "line": 13,
            "name": "Elements are overlapping",
            "match": {
              "location": "com.apec.stepDefinitions.Bug604Stepdefs.elementsAreOverlapping()"
            },
            "keyword": "Then "
          }
        ]
      },
      {
        "line": 3,
        "name": "go to apec home page",
        "description": "",
        "type": "background",
        "keyword": "Background",
        "steps": [
          {
            "result": {
              "duration": 8846000000,
              "status": "passed"
            },
            "line": 4,
            "name": "User is on Apec home page",
            "match": {
              "location": "com.apec.stepDefinitions.Bug621Stepdefs.userIsOnApecHomePage()"
            },
            "keyword": "Given "
          }
        ]
      },
      {
        "start_timestamp": "2021-06-11T15:25:33.007Z",
        "before": [
          {
            "result": {
              "duration": 1899000000,
              "status": "passed"
            },
            "match": {
              "location": "com.apec.stepDefinitions.CucumberHooks.setup()"
            }
          }
        ],
        "line": 29,
        "name": "Bug 620 Appointment center not stored in memory",
        "description": "",
        "id": "apec-bugs;bug-620-appointment-center-not-stored-in-memory;;2",
        "after": [
          {
            "result": {
              "duration": 10001000000,
              "status": "passed"
            },
            "match": {
              "location": "com.apec.stepDefinitions.CucumberHooks.teardown()"
            }
          }
        ],
        "type": "scenario",
        "keyword": "Scenario Outline",
        "steps": [
          {
            "result": {
              "duration": 9479000000,
              "status": "passed"
            },
            "line": 20,
            "name": "login to Apec with yoanntagne45@gmail.com and 1995P@oyonyoann",
            "match": {
              "arguments": [
                {
                  "val": "yoanntagne45@gmail.com",
                  "offset": 19
                },
                {
                  "val": "1995P@oyonyoann",
                  "offset": 46
                }
              ],
              "location": "com.apec.stepDefinitions.Bug620Stepdefs.loginToApecWithEmailAndPassword(java.lang.String,java.lang.String)"
            },
            "keyword": "And "
          },
          {
            "result": {
              "duration": 5483000000,
              "status": "passed"
            },
            "line": 21,
            "name": "User clicked on mon centre",
            "match": {
              "location": "com.apec.stepDefinitions.Bug620Stepdefs.userClickedOnMonCentre()"
            },
            "keyword": "And "
          },
          {
            "result": {
              "duration": 2095000000,
              "status": "passed"
            },
            "line": 22,
            "name": "User entered 38000",
            "match": {
              "arguments": [
                {
                  "val": "38000",
                  "offset": 13
                }
              ],
              "location": "com.apec.stepDefinitions.Bug620Stepdefs.userEnteredPostalcode(java.lang.String)"
            },
            "keyword": "And "
          },
          {
            "result": {
              "duration": 16184000000,
              "status": "passed"
            },
            "line": 23,
            "name": "User click on Centre apec grenoble in results",
            "match": {
              "location": "com.apec.stepDefinitions.Bug620Stepdefs.userClickOnCentreApecGrenobleInResults()"
            },
            "keyword": "When "
          },
          {
            "result": {
              "duration": 6093000000,
              "status": "passed"
            },
            "line": 24,
            "name": "User clicked on Prenez rendez-vous",
            "match": {
              "location": "com.apec.stepDefinitions.Bug620Stepdefs.userClickedOnPrenezRendezVous()"
            },
            "keyword": "And "
          },
          {
            "result": {
              "duration": 42810000000,
              "status": "passed"
            },
            "line": 25,
            "name": "Appointment center should be stored in memory",
            "match": {
              "location": "com.apec.stepDefinitions.Bug620Stepdefs.appointmentCenterShouldBeStoredInMemory()"
            },
            "keyword": "Then "
          }
        ]
      }
    ],
    "name": "Apec Bugs",
    "description": "",
    "id": "apec-bugs",
    "keyword": "Feature",
    "uri": "file:src/test/resources/features/Apec.feature",
    "tags": []
  }
]